django_tigger/__init__.py
django_tigger/exceptions.py
django_tigger/middleware.py
django_tigger-1.1.0.dist-info/DESCRIPTION.rst
django_tigger-1.1.0.dist-info/METADATA
django_tigger-1.1.0.dist-info/RECORD
django_tigger-1.1.0.dist-info/WHEEL
django_tigger-1.1.0.dist-info/metadata.json
django_tigger-1.1.0.dist-info/top_level.txt
