Metadata-Version: 2.0
Name: django-tigger
Version: 1.1.0
Summary: Bounce users out of your view by raising an exception
Home-page: https://github.com/danielquinn/django-tigger
Author: Daniel Quinn
Author-email: code@danielquinn.org
License: AGPLv3
Download-URL: https://github.com/danielquinn/django-tigger
Platform: UNKNOWN
Classifier: Operating System :: POSIX
Classifier: Operating System :: Unix
Classifier: Programming Language :: Python
Classifier: Programming Language :: Python :: 2.7
Classifier: Programming Language :: Python :: 3.4
Classifier: Programming Language :: Python :: 3.5
Classifier: Programming Language :: Python :: 3.6
Classifier: Topic :: Internet :: WWW/HTTP
Requires-Dist: Django (>=1.11)
